{
  "name": "Cinematic",
  "website": "https://www.instagram.com/cinematicstudioven/",
  "deployUrl": "https://cinematic.mundial.click",
  "logoPath": "/logo.svg",
  "drawerLogoPath": "/logo.svg",
  "instagram": "https://www.instagram.com/cinematicstudioven/",
  "whatsapp": "http://wa.me/+584141570762",
  "facebook": "",
  "linkedin": "",
  "tiktok": "",
  "youtube": "",
  "x": "",
  "email": "",
  "address": "Centro Comercial Cima, Alto Barinas, Barinas, Venezuela.",
  "googleMaps": "https://maps.app.goo.gl/3YfBXzseqw2SjHuR6",
  "hasQuiniela": true,
  "quinielaTitle": "⚽ Gran Quiniela Cinematic 🏆",
  "quinielaDescription": "Acierta el 1er y 2do lugar del Mundial y gana increíbles premios con nosotros.",
  "quinielaId": "cinematic",
  "quinielaEndDate": "2026-06-11T23:59:00Z",
  "quinielaPrizeImage": "/premio.png",
  "theme": "dark",
  "colors": {
    "appBg": "#252525",
    "splashBg": "linear-gradient(135deg, #252525 0%, #252525 50%, #252525 100%)",
    "headerBg": "#f5f5f5",
    "headerText": "#252525",
    "navBg": "#f5f5f5",
    "navText": "#252525",
    "navIcon": "#252525",
    "navIconActive": "#d52926",
    "drawerBg": "#f5f5f5"
  },
  "seo": {
    "defaultTitle": "Mundial 2026 | Cinematic",
    "titleTemplate": "Mundial 2026 | Cinematic",
    "description": "Todo sobre el Mundial FIFA 2026: calendario completo, horarios, resultados en vivo, tabla de posiciones, grupos y fase final. Sigue a las selecciones, las fechas de los partidos y cada detalle del evento deportivo más esperado.",
    "keywords": "mundial 2026, calendario mundial 2026, resultados mundial 2026, grupos mundial 2026, fase final mundial 2026, selecciones mundial 2026, horarios mundial 2026, tabla posiciones mundial 2026",
    "ogImage": "/ogimage.png"
  },
  "showBanner": false,
  "bannerDuration": 5,
  "banner1url": "",
  "banner2url": "",
  "banner3url": "",
  "banner4url": "",
  "banner5url": ""
}